Description.rst
LICENSE
MANIFEST.in
README.rst
setup.py
sppy/TemplateExpander.py
sppy/__init__.py
sppy/benchmark.py
sppy/csarray.cpp
sppy/csarray.pyx
sppy/csarray1d_base.pxd
sppy/csarray1d_base.pyx
sppy/csarray1d_sub.cpp
sppy/csarray1d_sub.pxd
sppy/csarray1d_sub.pyx
sppy/csarray_base.pxd
sppy/csarray_base.pyx
sppy/csarray_sub.cpp
sppy/csarray_sub.pxd
sppy/csarray_sub.pyx
sppy/dtype.py
sppy/util.py
sppy/version.py
sppy.egg-info/PKG-INFO
sppy.egg-info/SOURCES.txt
sppy.egg-info/dependency_links.txt
sppy.egg-info/requires.txt
sppy.egg-info/top_level.txt
sppy/include/SparseMatrixExt.h
sppy/include/SparseVectorExt.h
sppy/io/__init__.py
sppy/io/matrix_market.py
sppy/io/profile/__init__.py
sppy/io/profile/ioProfile.py
sppy/io/test/__init__.py
sppy/io/test/testMatrix_market.py
sppy/lib/Parameter.py
sppy/lib/Util.py
sppy/lib/__init__.py
sppy/lib/test/ParameterTest.py
sppy/lib/test/__init__.py
sppy/linalg/GeneralLinearOperator.py
sppy/linalg/__init__.py
sppy/linalg/core.py
sppy/linalg/profile/GeneralLinearOperatorProfile.py
sppy/linalg/profile/__init__.py
sppy/linalg/test/GeneralLinearOperatorTest.py
sppy/linalg/test/__init__.py
sppy/linalg/test/coreTest.py
sppy/profile/__init__.py
sppy/profile/csarrayProfile.py
sppy/test/SparseMatrixExtTest.cpp
sppy/test/SparseVectorExtTest.cpp
sppy/test/__init__.py
sppy/test/csarrayTest.py
sppy/test/utilTest.py