Metadata-Version: 1.1
Name: sppy
Version: 0.6.7
Summary: UNKNOWN
Home-page: http://packages.python.org/sppy/
Author: Charanpal Dhanjal
Author-email: charanpal@gmail.com
License: GNU Library or Lesser General Public License (LGPL)
Keywords: numpy,sparse matrix
Platform: OS Independent
Classifier: Development Status :: 4 - Beta
Classifier: Intended Audience :: Developers
Classifier: License :: OSI Approved :: GNU Library or Lesser General Public License (LGPL)
Classifier: Operating System :: OS Independent
Classifier: Programming Language :: Python
